troposphere_mate/__init__.py
troposphere_mate/__init__.pyc
troposphere_mate/_version.py
troposphere_mate/_version.pyc
troposphere_mate/accessanalyzer.py
troposphere_mate/amazonmq.py
troposphere_mate/amplify.py
troposphere_mate/analytics.py
troposphere_mate/apigateway.py
troposphere_mate/apigatewayv2.py
troposphere_mate/applicationautoscaling.py
troposphere_mate/appmesh.py
troposphere_mate/appstream.py
troposphere_mate/appsync.py
troposphere_mate/ask.py
troposphere_mate/athena.py
troposphere_mate/autoscaling.py
troposphere_mate/autoscalingplans.py
troposphere_mate/awslambda.py
troposphere_mate/backup.py
troposphere_mate/batch.py
troposphere_mate/budgets.py
troposphere_mate/certificatemanager.py
troposphere_mate/cloud9.py
troposphere_mate/cloudformation.py
troposphere_mate/cloudfront.py
troposphere_mate/cloudtrail.py
troposphere_mate/cloudwatch.py
troposphere_mate/codebuild.py
troposphere_mate/codecommit.py
troposphere_mate/codedeploy.py
troposphere_mate/codepipeline.py
troposphere_mate/codestar.py
troposphere_mate/codestarnotifications.py
troposphere_mate/cognito.py
troposphere_mate/compat.py
troposphere_mate/config.py
troposphere_mate/constants.py
troposphere_mate/datapipeline.py
troposphere_mate/dax.py
troposphere_mate/directoryservice.py
troposphere_mate/dlm.py
troposphere_mate/dms.py
troposphere_mate/docdb.py
troposphere_mate/dynamodb.py
troposphere_mate/dynamodb2.py
troposphere_mate/ec2.py
troposphere_mate/ecr.py
troposphere_mate/ecs.py
troposphere_mate/efs.py
troposphere_mate/eks.py
troposphere_mate/elasticache.py
troposphere_mate/elasticbeanstalk.py
troposphere_mate/elasticloadbalancing.py
troposphere_mate/elasticloadbalancingv2.py
troposphere_mate/elasticsearch.py
troposphere_mate/emr.py
troposphere_mate/events.py
troposphere_mate/eventschemas.py
troposphere_mate/firehose.py
troposphere_mate/fsx.py
troposphere_mate/gamelift.py
troposphere_mate/glue.py
troposphere_mate/greengrass.py
troposphere_mate/guardduty.py
troposphere_mate/iam.py
troposphere_mate-0.0.14.dist-info/AUTHORS.rst
troposphere_mate-0.0.14.dist-info/LICENSE.txt
troposphere_mate-0.0.14.dist-info/METADATA
troposphere_mate-0.0.14.dist-info/WHEEL
troposphere_mate-0.0.14.dist-info/top_level.txt
troposphere_mate-0.0.14.dist-info/RECORD
