Metadata-Version: 2.1
Name: troposphere-mate
Version: 0.0.14
Summary: Orchestrate AWS Resource in Pythonic Way.
Home-page: https://github.com/MacHu-GWU/
Author: Sanhe Hu
Author-email: husanhe@gmail.com
Maintainer: Unknown
License: MIT
Download-URL: https://pypi.python.org/pypi/troposphere_mate/0.0.14#downloads
Platform: Windows
Platform: MacOS
Platform: Unix
Classifier: Development Status :: 4 - Beta
Classifier: Intended Audience :: Developers
Classifier: License :: OSI Approved :: MIT License
Classifier: Natural Language :: English
Classifier: Operating System :: Microsoft :: Windows
Classifier: Operating System :: MacOS
Classifier: Operating System :: Unix
Classifier: Programming Language :: Python
Classifier: Programming Language :: Python :: 2.7
Classifier: Programming Language :: Python :: 3.4
Classifier: Programming Language :: Python :: 3.5
Classifier: Programming Language :: Python :: 3.6
Classifier: Programming Language :: Python :: 3.7
Requires-Dist: troposphere (==2.5.3)
Requires-Dist: typing
Requires-Dist: picage
Requires-Dist: pathlib-mate
Requires-Dist: superjson
Requires-Dist: configirl
Requires-Dist: typing ; python_version == "2.7"
Provides-Extra: docs
Requires-Dist: sphinx (==1.8.1) ; extra == 'docs'
Requires-Dist: sphinx-rtd-theme ; extra == 'docs'
Requires-Dist: sphinx-jinja ; extra == 'docs'
Requires-Dist: sphinx-copybutton ; extra == 'docs'
Requires-Dist: docfly (>=0.0.17) ; extra == 'docs'
Requires-Dist: rstobj (>=0.0.5) ; extra == 'docs'
Requires-Dist: pygments ; extra == 'docs'
Provides-Extra: tests
Requires-Dist: pytest (==3.2.3) ; extra == 'tests'
Requires-Dist: pytest-cov (==2.5.1) ; extra == 'tests'
Requires-Dist: pathlib-mate ; extra == 'tests'
Requires-Dist: picage ; extra == 'tests'
Requires-Dist: jinja2 ; extra == 'tests'
